{
    "labels/element[name='gmd:MD_ScopeCode']": "Codi de l'abast",
    "labels/element[name='code' and id='207.0' and context='gmd:MD_Identifier']": "Codi",
    "labels/element[name='code']": "Codi del sistema",
    "labels/element[name='code' and id='547.0' and context='gmd:MD_CodeValue']": "Codi",
    "labels/element[name='codeSpace' and id='208.1']": "Autoritat de referència",
    "labels/element[name='gco:Date' and id='364.0' and context='gmd:CI_Citation']": "Dada d'edició",
    "labels/element[name='gco:Date' and id='393.0']": "Data",
    "labels/element[name='gco:DateTime' and id='64.0' and context='gmd:MD_Usage']": "Data i hora d'ús",
    "labels/element[name='gco:DateTime' and id='300.0' and context='gmd:MD_StandardOrderProcess']": "Data i hora planejada de disponibilitat",
    "labels/element[name='gco:DateTime']": "Data i hora",
    "labels/element[name='gco:Measure' and id='100.0' and context='gmd:DQ_Element']": "Nom de la mesura",
    "labels/element[name='gco:Measure' and id='357.0' and context='gmd:EX_VerticalExtent']": "Unitat de mesura",
    "labels/element[name='gmd:CI_Address' and id='380.0']": "Adreça",
    "labels/element[name='gmd:CI_Citation' and id='359.0']": "Citació",
    "labels/element[name='gmd:CI_Contact' and id='387.0']": "Contacte",
    "labels/element[name='gmd:CI_Date' and id='393.0']": "Data",
    "labels/element[name='gmd:CI_OnlineResource' and id='396.0']": "Recurs en línia",
    "labels/element[name='gmd:CI_ResponsibleParty' and id='374.0']": "Part responsable",
    "labels/element[name='gmd:CI_Series' and id='403.0']": "Sèries",
    "labels/element[name='gmd:CI_Telephone' and id='407.0']": "Telèfon",
    "labels/element[name='gmd:DQ_AbsoluteExternalPositionalAccuracy' and id='117.0']": "Precisió absoluta de la posició externa",
    "labels/element[name='gmd:DQ_AccuracyOfATimeMeasurement' and id='121.0']": "Precisió en la mesura del temps",
    "labels/element[name='gmd:DQ_CompletenessCommission' and id='109.0']": "Comisió de la completitud",
    "labels/element[name='gmd:DQ_CompletenessOmission' and id='110.0']": "Omisió de la completitud",
    "labels/element[name='gmd:DQ_ConceptualConsistency' and id='112.0']": "Consistència conceptual",
    "labels/element[name='gmd:DQ_ConformanceResult' and id='129.0']": "Conformitat del resultat",
    "labels/element[name='gmd:DQ_DataQuality' and id='78.0']": "Qualitat de la dada",
    "labels/element[name='gmd:DQ_DomainConsistency' and id='113.0']": "Consistència del domini",
    "labels/element[name='gmd:DQ_FormatConsistency' and id='114.0']": "Consistència del format",
    "labels/element[name='gmd:DQ_GriddedDataPositionalAccuracy' and id='118.0']": "Precisió de la posició de les dades en malla",
    "labels/element[name='gmd:DQ_NonQuantitativeAttributeAccuracy' and id='126.0']": "Precisió dels atributs no quantitatius",
    "labels/element[name='gmd:DQ_QuantitativeAttributeAccuracy' and id='127.0']": "Precisió de l'atribut quantitatiu",
    "labels/element[name='gmd:DQ_QuantitativeResult' and id='133.0']": "Resultat quantitatiu",
    "labels/element[name='gmd:DQ_RelativeInternalPositionalAccuracy' and id='119.0']": "Precisió de la posició relativa interna",
    "labels/element[name='gmd:DQ_Scope' and id='138.0']": "Abast",
    "labels/element[name='gmd:DQ_TemporalConsistency' and id='122.0']": "Consistència temporal",
    "labels/element[name='gmd:DQ_TemporalValidity' and id='123.0']": "Validesa temporal",
    "labels/element[name='gmd:DQ_ThematicClassificationCorrectness' and id='125.0']": "Exactitud de la classificació temàtica",
    "labels/element[name='gmd:DQ_TopologicalConsistency' and id='115.0']": "Consistència topològica",
    "labels/element[name='gmd:EX_BoundingPolygon' and id='341.0']": "Polígon delimitador",
    "labels/element[name='gmd:EX_Extent' and id='334.0']": "Extensió",
    "labels/element[name='gmd:EX_GeographicBoundingBox' and id='343.0']": "Extensió geogràfica",
    "labels/element[name='gmd:EX_GeographicDescription' and id='348.0']": "Descripció geogràfica",
    "labels/element[name='gmd:EX_SpatialTemporalExtent' and id='352.0']": "Extensió espacial i temporal",
    "labels/element[name='gmd:EX_TemporalExtent' and id='350.0']": "Extensió temporal",
    "labels/element[name='gmd:EX_VerticalExtent' and id='354.0']": "Extensió vertical",
    "labels/element[name='gmd:ISBN' and id='372.0']": "ISBN",
    "labels/element[name='gmd:ISSN' and id='373.0']": "ISSN",
    "labels/element[name='gmd:LI_Lineage' and id='82.0']": "Llinatge",
    "labels/element[name='gmd:LI_ProcessStep' and id='86.0']": "Etapa del processat",
    "labels/element[name='gmd:LI_Source' and id='92.0']": "Origen",
    "labels/element[name='gmd:MD_AggregateInformation' and id='66.1']": "Informació agregada",
    "labels/element[name='gmd:MD_ApplicationSchemaInformation' and id='320.0']": "Informació de l'esquema d'aplicació",
    "labels/element[name='gmd:MD_Band' and id='259.0']": "Banda",
    "labels/element[name='gmd:MD_BrowseGraphic' and id='48.0']": "Gràfic de navegació",
    "labels/element[name='gmd:MD_Constraints' and id='67.0']": "Restriccions",
    "labels/element[name='gmd:MD_CoverageDescription' and id='239.0']": "Descripció de la cobertura",
    "labels/element[name='gmd:MD_DataIdentification' and id='36.0']": "Identificació de la dada",
    "labels/element[name='gmd:MD_DigitalTransferOptions' and id='274.0']": "Opcions de transferència digital",
    "labels/element[name='gmd:MD_Dimension' and id='179.0']": "Dimensió",
    "labels/element[name='gmd:MD_Distribution' and id='270.0']": "Distribució",
    "labels/element[name='gmd:MD_Distributor' and id='279.0']": "Distribuïdor",
    "labels/element[name='gmd:MD_ExtendedElementInformation' and id='306.0']": "Informació de l'element extès",
    "labels/element[name='gmd:MD_FeatureCatalogueDescription' and id='233.0']": "Descripció del catàleg de features",
    "labels/element[name='gmd:MD_Format' and id='284.0']": "Format",
    "labels/element[name='gmd:MD_GeometricObjects' and id='183.0']": "Objectes geomètrics",
    "labels/element[name='gmd:MD_Georectified' and id='162.0']": "Georrectificació",
    "labels/element[name='gmd:MD_Georeferenceable' and id='170.0']": "Georreferenciable",
    "labels/element[name='gmd:MD_GridSpatialRepresentation' and id='157.0']": "Representació espacial en malla",
    "labels/element[name='gmd:MD_Identifier' and id='205.0']": "Identificador",
    "labels/element[name='gmd:MD_ImageDescription' and id='243.0']": "Descripció de la imatge",
    "labels/element[name='gmd:MD_Keywords' and id='52.0']": "Paraules clau",
    "labels/element[name='gmd:MD_LegalConstraints' and id='69.0']": "Restriccions legals",
    "labels/element[name='gmd:MD_MaintenanceInformation' and id='142.0']": "Informació de manteniment",
    "labels/element[name='gmd:MD_Medium' and id='291.0']": "Mitjà",
    "labels/element[name='gmd:MD_Metadata' and id='1.0']": "Metadada",
    "labels/element[name='gmd:MD_MetadataExtensionInformation' and id='303.0']": "Informació de l'extensió de la metadada",
    "labels/element[name='gmd:MD_PortrayalCatalogueReference' and id='268.0']": "Referència al catàleg de representació",
    "labels/element[name='gmd:MD_RangeDimension' and id='256.0']": "Rang de la dimensió",
    "labels/element[name='gmd:MD_ReferenceSystem' and id='186.0']": "Sistema de referència",
    "labels/element[name='gmd:MD_RepresentativeFraction' and id='56.0']": "Fracció representativa",
    "labels/element[name='gmd:MD_Resolution' and id='59.0']": "Resolució",
    "labels/element[name='gmd:MD_ScopeDescription' and id='149.0']": "Descripció de l'abast",
    "labels/element[name='gmd:MD_SecurityConstraints' and id='73.0']": "Restriccions de seguretat",
    "labels/element[name='gmd:MD_ServiceIdentification' and id='47.0']": "Identificació del servei",
    "labels/element[name='gmd:MD_StandardOrderProcess' and id='298.0']": "Procés de comanda estàndard",
    "labels/element[name='gmd:MD_Usage' and id='62.0']": "Ús",
    "labels/element[name='gmd:MD_VectorSpatialRepresentation' and id='176.0']": "Representació vectorial espacial",
    "labels/element[name='gmd:PT_FreeText' and id='601.0']": "Text lliure",
    "labels/element[name='gmd:RS_Identifier' and id='208.0']": "Identificador",
    "labels/element[name='gmd:URL' and id='608.0']": "URL",
    "labels/element[name='gmd:abstract' and id='25.0']": "Extracte",
    "labels/element[name='gmd:accessConstraints' and id='70.0']": "Restriccions d'accés",
    "labels/element[name='gmd:address' and id='525.0' and context='gmd:CI_ResponsibleParty']": "Adreça",
    "labels/element[name='gmd:address' and id='389.0']": "Adreça",
    "labels/element[name='gmd:administrativeArea' and id='383.0']": "Àrea administrativa",
    "labels/element[name='gmd:aggregateDataSetIdentifier' and id='66.3']": "Identificador del conjunt de dades agregades",
    "labels/element[name='gmd:aggregateDataSetName' and id='66.2']": "Nom del conjunt de dades agregades",
    "labels/element[name='gmd:aggregationInfo' and id='35.1']": "Informació agregada",
    "labels/element[name='gmd:alternateTitle' and id='361.0']": "Títol alternatiu",
    "labels/element[name='gmd:amendmentNumber' and id='287.0']": "Nombre d'esmena",
    "labels/element[name='gmd:applicationProfile' and id='399.0']": "Perfil de l'aplicació",
    "labels/element[name='gmd:applicationSchemaInfo' and id='21.0']": "Informació de l'esquema de l'aplicació",
    "labels/element[name='gmd:associationType' and id='66.4']": "Tipus d'associació",
    "labels/element[name='gmd:attributeDescription' and id='240.0']": "Descripció de l'atribut",
    "labels/element[name='gmd:attributeInstances' and id='153.0']": "Instàncies de l'atribut",
    "labels/element[name='gmd:attributes' and id='150.0']": "Atributs",
    "labels/element[name='gmd:authority' and id='206.0']": "Autoritat",
    "labels/element[name='gmd:axisDimensionProperties' and id='159.0']": "Propietats de les dimensions de l'eix",
    "labels/element[name='gmd:bitsPerValue' and id='264.0']": "Bits per valor",
    "labels/element[name='gmd:cameraCalibrationInformationAvailability' and id='253.0']": "Disponibilitat de la informació de la calibració de la càmera",
    "labels/element[name='gmd:cellGeometry' and id='160.0']": "Geometria de la cel·la",
    "labels/element[name='gmd:centerPoint' and id='166.0']": "Centroide",
    "labels/element[name='gmd:characterSet' and id='4.0' and context='gmd:MD_Metadata']": "Codificació",
    "labels/element[name='gmd:characterSet' and id='40.0' and context='gmd:MD_DataIdentification']": "Codificació",
    "labels/element[name='gmd:characterSet' and id='4.0']": "Codificació",
    "labels/element[name='gmd:checkPointAvailability' and id='163.0']": "Disponibilitat de punts de control",
    "labels/element[name='gmd:checkPointDescription' and id='164.0']": "Descripció dels punts de control",
    "labels/element[name='gmd:citation' and id='24.0' and context='gmd:MD_Identification']": "Citació",
    "labels/element[name='gmd:citation' and id='576.0' and context='gmd:MD_Authority']": "Citació",
    "labels/element[name='gmd:citation' and id='581.0' and context='gmd:MD_Thesaurus']": "Citació",
    "labels/element[name='gmd:citation' and id='581.0']": "Citació",
    "labels/element[name='gmd:citedResponsibleParty' and id='367.0']": "Part responsable",
    "labels/element[name='gmd:city' and id='382.0']": "Ciutat",
    "labels/element[name='gmd:classification' and id='74.0']": "Classificació",
    "labels/element[name='gmd:classificationSystem' and id='76.0']": "Sistema de classificació",
    "labels/element[name='gmd:cloudCoverPercentage' and id='248.0']": "Percentatge de cobertura de núvols",
    "labels/element[name='gmd:code' and id='207.0' and context='gmd:RS_Identifier']": "Identificador únic del recurs",
    "labels/element[name='gmd:code' and id='207.0' and context='gmd:MD_Identifier']": "Codi",
    "labels/element[name='gmd:code' and id='547.0' and context='gmd:MD_CodeValue']": "Codi",
    "labels/element[name='gmd:codeSpace' and id='208.1']": "Espai de codis",
    "labels/element[name='gmd:collectiveTitle' and id='371.0']": "Títol col·lectiu",
    "labels/element[name='gmd:complianceCode' and id='234.0']": "Codi de conformitat",
    "labels/element[name='gmd:compressionGenerationQuantity' and id='250.0']": "Quantitat de generacions de compressió",
    "labels/element[name='gmd:condition' and id='312.0']": "Condició",
    "labels/element[name='gmd:constraintLanguage' and id='323.0']": "Restricció d'idioma",
    "labels/element[name='gmd:contact' and id='8.0' and context='gmd:MD_Metadata']": "Contacte",
    "labels/element[name='gmd:contact' and id='148.1' and context='gmd:MD_MaintenanceInformation']": "Contacte",
    "labels/element[name='gmd:contact' and id='8.0']": "Autor de la metadada",
    "labels/element[name='gmd:contactInfo' and id='378.0']": "Informació de contacte",
    "labels/element[name='gmd:contactInstructions' and id='392.0']": "Instruccions de contacte",
    "labels/element[name='gmd:contentInfo' and id='16.0']": "Informació del contingut",
    "labels/element[name='gmd:contentType' and id='241.0']": "Tipus de contingut",
    "labels/element[name='gmd:controlPointAvailability' and id='171.0']": "Disponibilitat de punts de control",
    "labels/element[name='gmd:cornerPoints' and id='165.0']": "Punts de cantonada",
    "labels/element[name='gmd:country' and id='612.0']": "País",
    "labels/element[name='gmd:country' and id='508.0' and context='gmd:MD_Legislation']": "País",
    "labels/element[name='gmd:country' and id='605.0' and context='PT_Group']": "País",
    "labels/element[name='gmd:credit' and id='27.0']": "Crèdit",
    "labels/element[name='gmd:dataQualityInfo' and id='18.0']": "Informació de la qualitat de les dades",
    "labels/element[name='gmd:dataSetURI' and id='11.1']": "URI del conjunt de dades",
    "labels/element[name='gmd:dataType' and id='313.0']": "Tipus de dada",
    "labels/element[name='gmd:dataset' and id='154.0']": "Conjunt de dades",
    "labels/element[name='gmd:date' and id='570.0']": "Data",
    "labels/element[name='gmd:date' and id='570.0' and context='gmd:MD_Revision']": "Data de la darrera modificació",
    "labels/element[name='gmd:date' and id='144.0' and context='gmd:MD_MaintenanceInformation']": "Data de la propera modificació",
    "labels/element[name='gmd:date' and id='362.0' and context='gmd:CI_Citation']": "Data",
    "labels/element[name='gmd:date' and id='394.0' and context='gmd:CI_Date']": "Data",
    "labels/element[name='gmd:dateOfNextUpdate' and id='144.0']": "Data de la propera modificació",
    "labels/element[name='gmd:dateStamp' and id='9.0']": "Data",
    "labels/element[name='gmd:dateTime' and id='89.0']": "Data/Hora",
    "labels/element[name='gmd:dateTime' and id='89.0' and context='LI_ProcessStep']": "Data/Hora",
    "labels/element[name='gmd:dateTime' and id='106.0' and context='gmd:DQ_Element']": "Data/Hora",
    "labels/element[name='gmd:dateType' and id='395.0']": "Tipus de data",
    "labels/element[name='gmd:definition' and id='310.0']": "Definició",
    "labels/element[name='gmd:deliveryPoint' and id='381.0']": "Punt de lliurament",
    "labels/element[name='gmd:denominator' and id='57.0']": "Denominador",
    "labels/element[name='gmd:density' and id='293.0']": "Densitat",
    "labels/element[name='gmd:densityUnits' and id='294.0']": "Unitat de densitat",
    "labels/element[name='gmd:description' and id='561.0']": "Descripció",
    "labels/element[name='gmd:description' and id='561.0' and context='gmd:MD_AbstractClass']": "Descripció",
    "labels/element[name='gmd:description' and id='87.0' and context='LI_ProcessStep']": "Descripció",
    "labels/element[name='gmd:description' and id='93.0' and context='LI_Source']": "Descripció",
    "labels/element[name='gmd:description' and id='335.0' and context='gmd:EX_Extent']": "Descripció",
    "labels/element[name='gmd:description' and id='401.0' and context='gmd:CI_OnlineResource']": "Descripció",
    "labels/element[name='gmd:description' and id='541.0' and context='gmd:MD_CodeDomain']": "Descripció",
    "labels/element[name='gmd:description' and id='549.0' and context='gmd:MD_CodeValue']": "Descripció del valor",
    "labels/element[name='gmd:description' and id='552.0' and context='gmd:MD_Attribute']": "Descripció",
    "labels/element[name='gmd:description' and id='557.0' and context='gmd:MD_Role']": "Descripció",
    "labels/element[name='gmd:descriptiveKeywords' and id='33.0']": "Paraules clau descriptives",
    "labels/element[name='gmd:descriptor' and id='258.0']": "Descriptor",
    "labels/element[name='gmd:dimension' and id='242.0']": "Dimensió",
    "labels/element[name='gmd:dimensionName' and id='180.0']": "Nom de la dimensió",
    "labels/element[name='gmd:dimensionSize' and id='181.0']": "Mida de la dimensió",
    "labels/element[name='gmd:distance' and id='61.0']": "Distància",
    "labels/element[name='gmd:distributionFormat' and id='271.0']": "Format de la distribució",
    "labels/element[name='gmd:distributionInfo' and id='17.0']": "Informació de la distribució",
    "labels/element[name='gmd:distributionOrderProcess' and id='281.0']": "Distribució / procés de comanda",
    "labels/element[name='gmd:distributor' and id='272.0']": "Distribuïdor",
    "labels/element[name='gmd:distributorContact' and id='280.0']": "Contacte del distribuïdor",
    "labels/element[name='gmd:distributorFormat' and id='282.0']": "Format de distribució",
    "labels/element[name='gmd:distributorTransferOptions' and id='283.0']": "Opcions de transferència de la distribució",
    "labels/element[name='gmd:domainCode' and id='309.0']": "Codi del domini",
    "labels/element[name='gmd:domainOfValidity' and id='197.0']": "Domini de validesa",
    "labels/element[name='gmd:domainValue' and id='315.0']": "Valor del domini",
    "labels/element[name='gmd:eastBoundLongitude' and id='345.0']": "Límit est",
    "labels/element[name='gmd:edition' and id='363.0']": "Edició",
    "labels/element[name='gmd:editionDate' and id='364.0']": "Data d'edició",
    "labels/element[name='gmd:electronicMailAddress' and id='386.0']": "Adreça de correu electrònic",
    "labels/element[name='gmd:environmentDescription' and id='44.0']": "Descripció de l'entorn",
    "labels/element[name='gmd:equivalentScale' and id='60.0']": "Escala equivalent",
    "labels/element[name='gmd:errorStatistic' and id='136.0']": "Error estadístic",
    "labels/element[name='gmd:evaluationMethodDescription' and id='104.0']": "Descripció del mètode d'avaluació",
    "labels/element[name='gmd:evaluationMethodType' and id='103.0']": "Mètode d'avaluació",
    "labels/element[name='gmd:evaluationProcedure' and id='105.0']": "Procediment d'avaluació",
    "labels/element[name='gmd:explanation' and id='131.0']": "Explicació",
    "labels/element[name='gmd:extendedElementInformation' and id='305.0']": "Informació extensa de l'element",
    "labels/element[name='gmd:extensionOnLineResource' and id='304.0']": "Extensió dels recursos en línia",
    "labels/element[name='gmd:extent' and id='45.0' and context='gmd:MD_DataIdentification']": "Extensió",
    "labels/element[name='gmd:extent' and id='140.0' and context='gmd:DQ_Scope']": "Extensió",
    "labels/element[name='gmd:extent' and id='351.0' and context='gmd:EX_TemporalExtent']": "Extensió",
    "labels/element[name='gmd:extentTypeCode' and id='340.0']": "Codi del tipus d'extensió",
    "labels/element[name='gmd:facsimile' and id='409.0']": "Facsímil",
    "labels/element[name='gmd:featureCatalogueCitation' and id='238.0']": "Citació del catàleg de features",
    "labels/element[name='gmd:featureInstances' and id='152.0']": "Instàncies de features",
    "labels/element[name='gmd:featureTypes' and id='237.0']": "Tipus de features",
    "labels/element[name='gmd:features' and id='151.0']": "Features",
    "labels/element[name='gmd:fees' and id='299.0']": "Quotes",
    "labels/element[name='gmd:fileDecompressionTechnique' and id='289.0']": "Tècnica de descompressió del fitxer",
    "labels/element[name='gmd:fileDescription' and id='50.0']": "Descripció del fitxer",
    "labels/element[name='gmd:fileIdentifier' and id='2.0']": "Identificador del fitxer",
    "labels/element[name='gmd:fileName' and id='49.0']": "Nom del fitxer",
    "labels/element[name='gmd:fileType' and id='51.0']": "Tipus de fitxer",
    "labels/element[name='gmd:filmDistortionInformationAvailability' and id='254.0']": "Disponibilitat d'informació sobre la distorsió del negatiu",
    "labels/element[name='gmd:formatDistributor' and id='290.0']": "Format del distribuidor",
    "labels/element[name='gmd:function' and id='402.0']": "Funció",
    "labels/element[name='gmd:geographicElement' and id='336.0']": "Element geogràfic",
    "labels/element[name='gmd:geographicIdentifier' and id='349.0']": "Identificador geogràfic",
    "labels/element[name='gmd:geometricObjectCount' and id='185.0']": "Nombre d'objectes geomètrics",
    "labels/element[name='gmd:geometricObjectType' and id='184.0']": "Tipus d'objecte geomètric",
    "labels/element[name='gmd:geometricObjects' and id='178.0']": "Objectes geomètrics",
    "labels/element[name='gmd:georeferencedParameters' and id='174.0']": "Paràmetres georrererenciats",
    "labels/element[name='gmd:graphicOverview' and id='31.0']": "Mostra gràfica",
    "labels/element[name='gmd:graphicsFile' and id='325.0']": "Fitxer de gràfics",
    "labels/element[name='gmd:handlingDescription' and id='77.0']": "Descripció de la manipulació",
    "labels/element[name='gmd:hierarchyLevel' and id='6.0']": "Jerarquia",
    "labels/element[name='gmd:hierarchyLevelName' and id='7.0']": "Nom del nivell jeràrquic",
    "labels/element[name='gmd:hoursOfService' and id='391.0']": "Hores de servei",
    "labels/element[name='gmd:identificationInfo' and id='15.0']": "Informació d'identificació",
    "labels/element[name='gmd:identifier' and id='573.0']": "Identificador",
    "labels/element[name='gmd:identifier' and id='573.0' and context='gmd:CI_Citation']": "Identificador del contacte",
    "labels/element[name='gmd:identifier' and id='575.0' and context='gmd:MD_Authority']": "Identificador",
    "labels/element[name='gmd:illuminationAzimuthAngle' and id='245.0']": "Angle azimutal de la il·luminació",
    "labels/element[name='gmd:illuminationElevationAngle' and id='244.0']": "Angle elevació de la il·luminació",
    "labels/element[name='gmd:imageQualityCode' and id='247.0']": "Codi de la qualitat de la imatge",
    "labels/element[name='gmd:imagingCondition' and id='246.0']": "Condicions de formació d'imatges",
    "labels/element[name='gmd:includedWithDataset' and id='236.0']": "Inclòs al conjunt de dades",
    "labels/element[name='gmd:individualName' and id='375.0']": "Nom individual",
    "labels/element[name='gmd:initiativeType' and id='66.5']": "Tipus d'iniciativa",
    "labels/element[name='gmd:issueIdentification' and id='405.0']": "Identificador de l'assumpte",
    "labels/element[name='gmd:keyword' and id='53.0']": "Paraula clau",
    "labels/element[name='gmd:language' and id='3.0']": "Idioma de les metadades",
    "labels/element[name='gmd:language' and context='gmd:MD_DataIdentification' and id='39.0']": "Idioma",
    "labels/element[name='gmd:language' and context='gmd:MD_FeatureCatalogueDescription' and id='235.0']": "Idioma",
    "labels/element[name='gmd:lensDistortionInformationAvailability' and id='255.0']": "Disponibilitat d'informació sobre la distorsió de les lents",
    "labels/element[name='gmd:level' and id='139.0']": "Jerarquia",
    "labels/element[name='gmd:levelDescription' and id='141.0']": "Descripció del nivell",
    "labels/element[name='gmd:lineage' and id='81.0']": "Llinatge",
    "labels/element[name='gmd:linkage' and id='397.0']": "Enllaçament",
    "labels/element[name='gmd:maintenanceAndUpdateFrequency' and id='143.0']": "Manteniment i freqüència d'actualització",
    "labels/element[name='gmd:maintenanceNote' and id='148.0']": "Nota de manteniment",
    "labels/element[name='gmd:maxValue' and id='260.0']": "Valor màxim",
    "labels/element[name='gmd:maximumValue' and id='356.0']": "Valor màxim",
    "labels/element[name='gmd:measureDescription' and id='102.0']": "Descripció de la mesura",
    "labels/element[name='gmd:measureIdentification' and id='101.0']": "Identificador de la mesura",
    "labels/element[name='gmd:mediumFormat' and id='296.0']": "Format del medi",
    "labels/element[name='gmd:mediumNote' and id='297.0']": "Nota del medi",
    "labels/element[name='gmd:metadataConstraints' and id='20.0' and context='gmd:MD_Metadata']": "Limitacions de la metadada",
    "labels/element[name='gmd:metadataConstraints']": "Limitacions de la metadada",
    "labels/element[name='gmd:metadataExtensionInfo' and id='14.0']": "Informació de l'extensió de la metadada",
    "labels/element[name='gmd:metadataMaintenance' and id='22.0']": "Manteniment de la metadada",
    "labels/element[name='gmd:metadataStandardName' and id='10.0']": "Nom estàndard de la metadada",
    "labels/element[name='gmd:metadataStandardVersion' and id='11.0']": "Versió estàndard de la metadada",
    "labels/element[name='gmd:minValue' and id='261.0']": "Valor mínim",
    "labels/element[name='gmd:minimumValue' and id='355.0']": "Valor mínim",
    "labels/element[name='gmd:name' and context='gmd:MD_AbstractClass' and id='560.0']": "Nom",
    "labels/element[name='gmd:name' and context='gmd:MD_Medium' and id='292.0']": "Nom",
    "labels/element[name='gmd:name' and context='gmd:RS_ReferenceSystem' and id='196.0']": "Nom",
    "labels/element[name='gmd:name' and context='gmd:MD_Format' and id='285.0']": "Nom",
    "labels/element[name='gmd:name' and context='gmd:MD_ExtendedElementInformation' and id='307.0']": "Nom",
    "labels/element[name='gmd:name' and context='gmd:MD_ApplicationSchemaInformation' and id='321.0']": "Nom",
    "labels/element[name='gmd:name' and context='gmd:CI_OnlineResource' and id='400.0']": "Nom del recurs",
    "labels/element[name='gmd:name' and context='gmd:CI_Series' and id='404.0']": "Nom",
    "labels/element[name='gmd:name' and context='gmd:MD_CodeDomain' and id='537.0']": "Nom",
    "labels/element[name='gmd:name' and context='gmd:MD_CodeValue' and id='546.0']": "Nom",
    "labels/element[name='gmd:name' and context='gmd:MD_Attribute' and id='551.0']": "Nom",
    "labels/element[name='gmd:name' and context='gmd:MD_Role' and id='556.0']": "Nom",
    "labels/element[name='gmd:name']": "Nom",
    "labels/element[name='gmd:nameOfMeasure' and id='100.0']": "Nom de la mesura",
    "labels/element[name='gmd:northBoundLatitude' and id='347.0']": "Límit nord",
    "labels/element[name='gmd:numberOfDimensions' and id='158.0']": "Nombre de dimensions",
    "labels/element[name='gmd:obligation' and id='311.0']": "Obligació",
    "labels/element[name='gmd:offLine' and id='278.0']": "Offline",
    "labels/element[name='gmd:offset' and id='267.0']": "Offset",
    "labels/element[name='gmd:onLine' and id='277.0']": "Recurs en línia",
    "labels/element[name='gmd:onlineResource' and id='390.0']": "Pàgina web",
    "labels/element[name='gmd:orderingInstructions' and id='301.0']": "Instruccions de la comanda",
    "labels/element[name='gmd:organisationName' and id='376.0']": "Nom de l'Organització",
    "labels/element[name='gmd:orientationParameterAvailability' and id='172.0']": "Disponibilitat de paràmetres d'orientació",
    "labels/element[name='gmd:orientationParameterDescription' and id='173.0']": "Descripció de paràmetres d'orientació",
    "labels/element[name='gmd:other' and id='155.0']": "Altres",
    "labels/element[name='gmd:otherCitationDetails' and id='370.0']": "Altres detalls de la citació",
    "labels/element[name='gmd:otherConstraints' and id='72.0']": "Altres resriccions",
    "labels/element[name='gmd:page' and id='406.0']": "Pàgina",
    "labels/element[name='gmd:parameterCitation' and id='175.0']": "Citació de paràmetres",
    "labels/element[name='gmd:parentEntity' and id='316.0']": "Element pare",
    "labels/element[name='gmd:parentIdentifier' and id='5.0']": "Identificador del pare",
    "labels/element[name='gmd:pass' and id='132.0']": "Passa",
    "labels/element[name='gmd:peakResponse' and id='263.0']": "Pic de resposta",
    "labels/element[name='gmd:phone' and id='526.0']": "Telèfon",
    "labels/element[name='gmd:plannedAvailableDateTime' and id='300.0']": "Disponibilitat prevista",
    "labels/element[name='gmd:pointInPixel' and id='167.0']": "Punt al píxel",
    "labels/element[name='gmd:pointOfContact' and id='29.0']": "Punt de contacte",
    "labels/element[name='gmd:polygon' and id='342.0']": "Polígon",
    "labels/element[name='gmd:portrayalCatalogueCitation' and id='269.0']": "Citació del catàleg de representació",
    "labels/element[name='gmd:portrayalCatalogueInfo' and id='19.0']": "Informació del catàleg de representació",
    "labels/element[name='gmd:positionName' and id='377.0']": "Nom del càrrec",
    "labels/element[name='gmd:postalCode' and id='384.0']": "Codi postal",
    "labels/element[name='gmd:presentationForm' and id='368.0']": "Formulari de presentació",
    "labels/element[name='gmd:processStep' and id='84.0']": "Etapa del processat",
    "labels/element[name='gmd:processingLevelCode' and id='249.0']": "Codi del nivell de processament",
    "labels/element[name='gmd:processor' and id='90.0']": "Processador",
    "labels/element[name='gmd:protocol' and id='398.0']": "Protoco",
    "labels/element[name='gmd:purpose' and id='26.0']": "Propòsit",
    "labels/element[name='gmd:radiometricCalibrationDataAvailability' and id='252.0']": "Disponibilitat de dades sobre la calibració radiomètrica",
    "labels/element[name='gmd:rationale' and id='88.0']": "Raonament",
    "labels/element[name='gmd:rationale' and id='318.0' and context='gmd:MD_ExtendedElementInformation']": "Raonament",
    "labels/element[name='gmd:referenceSystemIdentifier' and id='187.0']": "Identificador del Sistema de Referència",
    "labels/element[name='gmd:referenceSystemInfo' and id='13.0']": "Informació del Sistema de Referència",
    "labels/element[name='gmd:report' and id='80.0']": "Informe",
    "labels/element[name='gmd:resolution' and id='182.0']": "Resolució",
    "labels/element[name='gmd:resourceConstraints' and id='35.0']": "Restriccions del recurs",
    "labels/element[name='gmd:resourceFormat' and id='32.0']": "Format del recurs",
    "labels/element[name='gmd:resourceMaintenance' and id='30.0']": "Manteniment dels recursos",
    "labels/element[name='gmd:resourceSpecificUsage' and id='34.0']": "Ús específic del recurs",
    "labels/element[name='gmd:result' and id='107.0']": "Resultat",
    "labels/element[name='gmd:role' and id='566.0' and context='gmd:MD_Association']": "Rol",
    "labels/element[name='gmd:role' and id='379.0']": "Rol",
    "labels/element[name='gmd:rule' and id='317.0']": "Regla",
    "labels/element[name='gmd:scaleDenominator' and id='94.0']": "Denominador d'escala",
    "labels/element[name='gmd:scaleFactor' and id='266.0']": "Factor d'escala",
    "labels/element[name='gmd:schemaAscii' and id='324.0']": "Esquema ASCII",
    "labels/element[name='gmd:schemaLanguage' and id='322.0']": "Esquema de l'idioma",
    "labels/element[name='gmd:scope' and id='79.0']": "Abast",
    "labels/element[name='gmd:sequenceIdentifier' and id='257.0']": "Identificador de la seqüència",
    "labels/element[name='gmd:series' and id='369.0']": "Sèries",
    "labels/element[name='gmd:shortName' and id='308.0']": "Nom curt",
    "labels/element[name='gmd:softwareDevelopmentFile' and id='326.0']": "Fitxer de desenvolupament de software",
    "labels/element[name='gmd:softwareDevelopmentFileFormat' and id='327.0']": "Format del fitxer de desenvolupament de software",
    "labels/element[name='gmd:source' and id='85.0']": "Origen",
    "labels/element[name='gmd:source' and id='319.0' and context='gmd:MD_ExtendedElementInformation']": "Origen",
    "labels/element[name='gmd:sourceCitation' and id='96.0']": "Citació de la font",
    "labels/element[name='gmd:sourceExtent' and id='97.0']": "Extensió de la font",
    "labels/element[name='gmd:sourceReferenceSystem' and id='95.0']": "Sistema de referència de la font",
    "labels/element[name='gmd:sourceStep' and id='98.0']": "Pas de la font",
    "labels/element[name='gmd:southBoundLatitude' and id='346.0']": "Límit sud",
    "labels/element[name='gmd:spatialExtent' and id='353.0']": "Extensió espacial",
    "labels/element[name='gmd:spatialRepresentationInfo' and id='12.0']": "Informació de la representació espacia",
    "labels/element[name='gmd:spatialRepresentationType' and id='37.0']": "Tipus de representació espacial",
    "labels/element[name='gmd:spatialResolution' and id='38.0']": "Resolució espacial",
    "labels/element[name='gmd:specificUsage' and id='63.0']": "Ús específic",
    "labels/element[name='gmd:specification' and id='130.0' and context='gmd:DQ_ConformanceResult']": "Especificació",
    "labels/element[name='gmd:specification' and id='288.0' and context='gmd:MD_Format']": "Especificació",
    "labels/element[name='gmd:specification']": "Especificació",
    "labels/element[name='gmd:statement' and id='83.0']": "Declaració",
    "labels/element[name='gmd:status' and id='28.0']": "Estat",
    "labels/element[name='gmd:supplementalInformation' and id='46.0']": "Informació suplementària",
    "labels/element[name='gmd:temporalElement' and id='337.0']": "Element temporal",
    "labels/element[name='gmd:textGroup' and id='602.0']": "Grup de text",
    "labels/element[name='gmd:thesaurusName' and id='55.0']": "Nom del tesaure",
    "labels/element[name='gmd:title' and id='360.0']": "Títol",
    "labels/element[name='gmd:title' and id='507.0' and context='gmd:MD_Legislation']": "Títol",
    "labels/element[name='gmd:toneGradation' and id='265.0']": "Gradació del to",
    "labels/element[name='gmd:topicCategory' and id='41.0']": "Categoria temàtica",
    "labels/element[name='gmd:MD_TopicCategoryCode']": "Codi de la categoria temàtica",
    "labels/element[name='gmd:topologyLevel' and id='177.0']": "Nivell topològic",
    "labels/element[name='gmd:transferOptions' and id='273.0']": "Opcions de transferència",
    "labels/element[name='gmd:transferSize' and id='276.0']": "Mida de la transferència",
    "labels/element[name='gmd:transformationDimensionDescription' and id='168.0']": "Descripció de la dimensió de transformació",
    "labels/element[name='gmd:transformationDimensionMapping' and id='169.0']": "Mapeig de la dimensió de transformació",
    "labels/element[name='gmd:transformationParameterAvailability' and id='161.0']": "Disponibilitat de paràmetres de transformació",
    "labels/element[name='gmd:triangulationIndicator' and id='251.0']": "indicador de triangulació",
    "labels/element[name='gmd:turnaround' and id='302.0']": "Gir en rodó",
    "labels/element[name='gmd:type' and id='54.0']": "Tipus",
    "labels/element[name='gmd:type' and id='540.0' and context='gmd:MD_CodeDomain']": "Tipus",
    "labels/element[name='gmd:type' and id='543.0' and context='gmd:MD_Type']": "Definició de tipus",
    "labels/element[name='gmd:units' and id='262.0']": "Unitat del valor",
    "labels/element[name='gmd:unitsOfDistribution' and id='275.0']": "Unitats de distribució",
    "labels/element[name='gmd:updateScope' and id='146.0']": "Abast de l'actualització",
    "labels/element[name='gmd:updateScopeDescription' and id='147.0']": "Descripció de l'abast de l'actualització",
    "labels/element[name='gmd:usageDateTime' and id='64.0']": "Dia i hora d'ús",
    "labels/element[name='gmd:useConstraints' and id='71.0']": "Restriccions d'ús",
    "labels/element[name='gmd:useLimitation' and id='68.0']": "Limitació de l'ús",
    "labels/element[name='gmd:userContactInfo' and id='66.0']": "Informació de contacte de l'usuari",
    "labels/element[name='gmd:userDefinedMaintenanceFrequency' and id='145.0']": "Freqüència de manteniment definida per l'usuari",
    "labels/element[name='gmd:userDeterminedLimitations' and id='65.0']": "Limitacions determinades per l'usuari",
    "labels/element[name='gmd:userNote' and id='75.0']": "Notes de l'usuari",
    "labels/element[name='gmd:value' and id='137.0' and context='gmd:DQ_QuantitativeResult']": "Valor",
    "labels/element[name='gmd:value']": "Valor",
    "labels/element[name='gmd:value' and id='544.0' and context='gmd:MD_Type']": "Valor",
    "labels/element[name='gmd:valueType' and id='134.0']": "Tipus de valor",
    "labels/element[name='gmd:valueUnit' and id='135.0']": "Unitat del valor",
    "labels/element[name='gmd:version' and id='208.2' and context='gmd:RS_Identifier']": "Versió",
    "labels/element[name='gmd:version' and id='286.0']": "Versió",
    "labels/element[name='gmd:verticalElement' and id='338.0']": "Element vertical",
    "labels/element[name='gmd:voice' and id='408.0']": "Veu",
    "labels/element[name='gmd:volumes' and id='295.0']": "Volums",
    "labels/element[name='gmd:westBoundLongitude' and id='344.0']": "Límit oest",
    "labels/element[name='gml:beginPosition']": "Data d'inici",
    "labels/element[name='gml:endPosition']": "Data de finalització",
    "labels/element[name='gml:relatedTime']": "Temps relacionat",
    "labels/element[name='gml:coordinates']": "Coordenades",
    "labels/element[name='gml:Polygon']": "Polígon",
    "labels/element[name='gml:Point']": "Punt",
    "labels/element[name='gml:LineString']": "Línia",
    "labels/element[name='gml:LinearRing']": "Anella",
    "labels/element[name='gml:exterior']": "Límit exterior",
    "labels/element[name='gml:interior']": "Límit interior",
    "labels/element[name='gml:begin']": "Inici",
    "labels/element[name='gml:end']": "Final",
    "labels/element[name='gml:duration']": "Durada",
    "labels/element[name='gml:timeInterval']": "Interval de temps",
    "labels/element[name='gml:name']": "Nom",
    "labels/element[name='gml:metaDataProperty']": "Propietat de la metadada",
    "labels/element[name='gml:identifier']": "Identificador",
    "labels/element[name='gml:description']": "Descripció",
    "labels/element[name='gml:descriptionReference']": "Descripció de referència",
    "labels/element[name='gml:TimeInstant']": "Instant de temps",
    "labels/element[name='gml:TimePosition']": "Posició temporal",
    "labels/element[name='gml:timePosition']": "Posició temporal",
    "labels/element[name='gml:TimePeriod']": "Període de temps",
    "labels/element[name='gml:TimeNode']": "Node de temps",
    "labels/element[name='gml:TimeEdge']": "Límit de temps",
    "labels/element[name='gml:ProjectedCRS']": "CRS projectat",
    "labels/element[name='gml:id']": "Identificador",
    "labels/element[name='gml:id' and id='191.0' and context='gmd:MD_CRS']": "El·lipsoide",
    "labels/element[name='id' and id='191.0']": "Identificador",
    "labels/element[name='indeterminatePosition']": "Posició indeterminada",
    "labels/element[name='frame']": "Marc",
    "labels/element[name='calendarEraName']": "Nom de l'era del calendari",
    "labels/element[name='unit']": "Unitat",
    "labels/element[name='radix']": "Base",
    "labels/element[name='factor']": "Factor",
    "labels/element[name='srv:SV_ServiceIdentification']": "Identificació del servei (19119)",
    "labels/element[name='srv:SV_ParameterDirection']": "Direcció del paràmetre",
    "labels/element[name='srv:serviceType']": "Tipus de servei",
    "labels/element[name='srv:serviceTypeVersion']": "Versió del servei",
    "labels/element[name='srv:accessProperties']": "Propietats d'accés",
    "labels/element[name='srv:restrictions']": "Restriccions",
    "labels/element[name='srv:containsOperations']": "Conté operacions",
    "labels/element[name='srv:operatesOn']": "Opera sobre",
    "labels/element[name='srv:operationName']": "Nom de l'operació",
    "labels/element[name='srv:SV_OperationMetadata']": "Operació",
    "labels/element[name='srv:DCP']": "Plataformes de computació distribuïda",
    "labels/element[name='srv:operationDescription']": "Descripció de la operació",
    "labels/element[name='srv:invocationName']": "Nom de la invocació",
    "labels/element[name='srv:parameters']": "Paràmetres",
    "labels/element[name='srv:SV_Parameter']": "Paràmetre",
    "labels/element[name='srv:direction']": "Direcció",
    "labels/element[name='srv:valueType']": "Tipus de valor",
    "labels/element[name='srv:connectPoint']": "Punt de connexió",
    "labels/element[name='srv:dependsOn']": "Depèn de",
    "labels/element[name='srv:providerName']": "Nom del proveïdor",
    "labels/element[name='srv:serviceContact']": "Contacte del servei",
    "labels/element[name='srv:name']": "Nom",
    "labels/element[name='srv:description']": "Descripció",
    "labels/element[name='srv:optionality']": "Opcionalitat",
    "labels/element[name='srv:repeatability']": "Repetibilitat",
    "labels/element[name='srv:coupledResource']": "Recurs acoblat",
    "labels/element[name='srv:SV_CoupledResource']": "Recurs acoblat",
    "labels/element[name='srv:identifier']": "Identificador",
    "labels/element[name='srv:couplingType']": "Tipus d'acoblament",
    "labels/element[name='srv:SV_CouplingType']": "Tipus d'acoblament",
    "labels/element[name='srv:extent']": "Extensió",
    "labels/element[name='srv:keywords']": "Paraules clau",
    "labels/element[name='gmd:locale']": "Altre idioma",
    "labels/element[name='gmd:describes']": "Descriu",
    "labels/element[name='gmd:propertyType']": "Tipus de propietat",
    "labels/element[name='gmd:PT_Locale']": "Localització",
    "labels/element[name='gmd:PT_LocaleContainer']": "PT_LocaleContainer",
    "labels/element[name='gmd:featureType']": "Tipus de feature",
    "labels/element[name='gmd:featureAttribute']": "Atribut de feature",
    "labels/element[name='gmd:DS_Association']": "DS_Association",
    "labels/element[name='gmd:DS_DataSet']": "DS_DataSet",
    "labels/element[name='gmd:DS_Initiative']": "DS_Initiative",
    "labels/element[name='gmd:DS_OtherAggregate']": "DS_OtherAggregate",
    "labels/element[name='gmd:DS_Platform']": "DS_Platform",
    "labels/element[name='gmd:DS_ProductionSeries']": "DS_ProductionSeries",
    "labels/element[name='gmd:DS_Sensor']": "DS_Sensor",
    "labels/element[name='gmd:DS_Series']": "DS_Series",
    "labels/element[name='gmd:DS_StereoMate']": "DS_StereoMate",
    "labels/element[name='gmd:languageCode']": "Idioma",
    "labels/element[name='gmd:LanguageCode']": "Codi d'idioma ISO",
    "labels/element[name='gmd:characterEncoding']": "Codificació de caracters",
    "labels/element[name='uuidref']": "UUID de la metadada",
    "labels/element[name='uom']": "Unitat de mesura",
    "labels/element[name='gco:Record']": "Registre",
    "labels/element[name='gco:Binary']": "Binari",
    "labels/element[name='gco:MemberName']": "Nom del membre",
    "labels/element[name='gco:aName']": "Nom",
    "labels/element[name='gco:aName' and context='gco:TypeName']": "Nom del tipus",
    "labels/element[name='gco:attributeType']": "Tipus d'atribut",
    "labels/element[name='gco:TypeName']": "Nom del tipus",
    "labels/element[name='gco:LocalName']": "Nom local",
    "labels/element[name='gco:ScopedName']": "Nom acotat",
    "labels/element[name='gmd:has']": "Té",
    "labels/element[name='gmd:MD_PixelOrientationCode']": "Codi de la orientació del píxel",
    "labels/element[name='gmd:MD_ObligationCode']": "Codi d'obligació",
    "labels/element[name='gmd:maximumOccurrence']": "Ocurrències màximes",
    "labels/element[name='gco:localName']": "Nom",
    "labels/element[name='gmd:composedOf']": "Composat per",
    "labels/element[name='gmd:partOf']": "Part de",
    "labels/element[name='gmd:seriesMetadata']": "Sèrie de metadades",
    "labels/element[name='gmd:subset']": "Subconjunt",
    "labels/element[name='gmd:superset']": "Superconjunt",
    "labels/element[name='gmd:CI_RoleCode']": "Codi de ro",
    "labels/element[name='gts:TM_PeriodDuration']": "Durada del període",
    "labels/element[name='gco:CharacterString']": "Text",
    "labels/element[name='gco:nilReason']": "Motiu de la nul·litat",
    "labels/element[name='srv:DCPList']": "Llista de plataformes de computació distribuïda",
    "labels/element[name='gmd:verticalCRS']": "CRS vertical",
    "labels/element[name='gmx:FileName']": "Nom del fitxer",
    "labels/element[name='src']": "URL de la font",
    "labels/element[name='gmx:Anchor']": "Anclatge",
    "labels/element[name='xlink:href']": "Href de l'enllaç",
    "labels/element[name='hidden-elements']": "Elements ocults",
    "labels/element[name='gmx:name']": "Nom",
    "labels/element[name='gmx:scope']": "Abast",
    "labels/element[name='gmx:versionNumber']": "Versió",
    "labels/element[name='gmx:versionDate']": "Data",
    "labels/element[name='gmx:fieldOfApplication']": "Camp d'aplicació",
    "labels/element[name='gml:axis']": "Eix",
    "labels/element[name='gml:axisAbbrev']": "Abreviació de l'eix",
    "labels/element[name='gml:axisDirection']": "Direcció de l'eix",
    "labels/element[name='gml:maximumValue']": "Valor màxim",
    "labels/element[name='gml:minimumValue']": "Valor mínim",
    "labels/element[name='gml:scope']": "Abast",
    "labels/element[name='gml:VerticalCRS']": "CRS vertical",
    "labels/element[name='gml:remarks']": "Observacions",
    "labels/element[name='gml:domainOfValidity']": "Domini de validesa",
    "labels/element[name='gml:verticalCS']": "CS vertical",
    "labels/element[name='gml:VerticalCS']": "CS vertical",
    "labels/element[name='gml:CoordinateSystemAxis']": "Eix del sistema de coordenades",
    "labels/element[name='gml:rangeMeaning']": "Signifcat del rang",
    "labels/element[name='gml:verticalDatum']": "Datum vertical",
    "labels/element[name='gml:VerticalDatum']": "Datum vertical",
    "labels/element[name='gml:realizationEpoch']": "Època de realització",
    "labels/element[name='gmd:MD_ProgressCode']": "Progrés",
    "labels/element[name='gmd:MD_MaintenanceFrequencyCode']": "Freqüència de manteniment",
    "labels/element[name='gmd:MD_SpatialRepresentationTypeCode']": "Tipus de representació espacial",
    "labels/element[name='gmd:MD_CharacterSetCode']": "Conjunt de caràcters",
    "labels/element[name='gmd:MD_TopologyLevelCode']": "Nivell de topologia",
    "labels/element[name='gmd:MD_GeometricObjectTypeCode']": "Tipus d'objecte geomètric",
    "labels/element[name='gmd:MD_RestrictionCode' and context='gmd:accessConstraints']": "Restricció d'accés",
    "labels/element[name='gmd:MD_RestrictionCode' and context='gmd:useConstraints']": "Restricció d'ús",
    "labels/element[name='gmd:DS_AssociationTypeCode']": "Tipus d'associaciṕ",
    "labels/element[name='gmd:DS_InitiativeTypeCode']": "Tipus d'iniciativa"
}