{
    "strings/understandResource": "Informacije o zbirki podatkov",
    "strings/relatedResources": "Povezane storitve in podatki",
    "strings/techInfo": "Tehnični podatki",
    "strings/contactInfo": "Točka za stike",
    "strings/mdContactInfo": "Kontakt za metapodatke",
    "strings/refDate": "Referenčni datum",
    "strings/temporalRef": "Informacija o časovni natančnosti",
    "strings/constraintInfo": "Opis pogojev dostopa",
    "strings/xml_iso19139": "Shrani metapodatek kot ISO19139 XML datoteko",
    "strings/xml_iso19139Tooai_dc": "Shrani metapodatek kot OAI Dublin Core xml",
    "strings/advanced": "Celotno",
    "strings/default": "Enostavno",
    "strings/simple": "Enostavno",
    "strings/inspire": "INSPIRE",
    "strings/resource": "Vir",
    "strings/xml": "XML pogled",
    "strings/metadata": "Metapodatek",
    "strings/identificationInfo": "Identifikacija",
    "strings/distributionInfo": "Distribucija",
    "strings/dataQualityInfo": "Kakovost",
    "strings/spatialRepresentationInfo": "Prostorska predstavitev",
    "strings/referenceSystemInfo": "Referenčni sistem",
    "strings/contentInfo": "Vsebina",
    "strings/portrayalCatalogueInfo": "Portrayal",
    "strings/metadataConstraints": "Md. constraints",
    "strings/metadataMaintenance": "Md. maintenance",
    "strings/applicationSchemaInfo": "Schema info",
    "strings/noThesaurusName": "Ključne besede",
    "strings/bboxesSection": "Geografski prostorski obseg",
    "strings/invalidElement": "Invalid element. Invalid content was found starting with element:",
    "strings/onElementOf": "Eden od naštetih elementov",
    "strings/isExpected": "je pričakovan.",
    "strings/isNotComplete": "ni popolno.",
    "strings/elementLocated": "Nadrejeni element je",
    "strings/missingElement": "Manjkajoči element. Vsebina:",
    "strings/invalidValue": "Napačna ali manjkajoča vrednost",
    "strings/notValidFor": "ni prava vrednost za",
    "strings/xsdErrorIs": "XSD napaka:",
    "strings/inElement": "v elementu",
    "strings/enum1": "Vrednost",
    "strings/enum2": "ni veljavna vrednost za",
    "strings/enum3": "Seznam vrednosti:",
    "strings/url": "Internetni naslov vira",
    "strings/identifier": "Identifikator vira",
    "strings/rsIdentifier": "Projekcija",
    "strings/referenceDate": "Informacija o časovni natančnosti",
    "strings/creationDate": "Nastanek",
    "strings/hierarchyLevel": "Vrsta vira",
    "strings/publicationDate": "Objavljeno",
    "strings/revisionDate": "Datum zadnje spremembe",
    "strings/temporalRangeSection": "Časovni obseg",
    "strings/beginPosition": "Začetek",
    "strings/endPosition": "Konec",
    "strings/conformity": "Skladnost",
    "strings/conformity_title": "Naslov",
    "strings/conformity_date": "Datum",
    "strings/explanation": "Pojasnilo",
    "strings/pass": "Skladnost",
    "strings/indeterminatePosition": "Indeterminate position",
    "strings/pointOfContact": "Kontakt za vir",
    "strings/metadataPointOfContact": "Metapodatkovni kontakt",
    "strings/organisationName": "Ime organizacije",
    "strings/electronicMailAddress": "E-mail",
    "strings/role": "Vloga",
    "strings/encoding": "Kodiranje",
    "strings/inspireTheme": "INSPIRE tematike",
    "strings/format": "Format",
    "strings/format_version": "Verzija",
    "strings/lineage": "Poreklo",
    "strings/spatialResolution": "Prostorska ločljivost (merilo)",
    "strings/spatialDistance": "Prostorska ločljivost (razdalja)",
    "strings/accessConstraints": "Omejitve javnega dostopa",
    "strings/useLimitation": "Omejitve uporabe",
    "strings/add-resource-id": "Izračunaj identifikator vira",
    "strings/add-resource-idHelp": "Compose the resource identifier using the catalog URL and the metadata identifier (eg. http://www.organization.org/catalogue/5391bf69-44bc-4ea0-8cc0-6cf6c3bc81ae).",
    "strings/add-extent-from-geokeywords": "Compute extent from keyword",
    "strings/add-extent-from-geokeywordsHelp": "Analyze each keyword of type place and add matching extent."
}