{
    "general": "عمومی",
    "kml-link": "فایل kml برای دانلود",
    "link-link": "اتصال",
    "download-link": "دانلود",
    "ogc-link": "WxS Links",
    "noFormatName": "بدون ساختار ارائه",
    "noThesaurusName": "نام اصطلاح نامه مشخص نشده",
    "wms-link": "Web Map Server",
    "associated-link": "مرتبط",
    "children-link": "Child",
    "datasets-link": "مجموعه داده ها",
    "hasfeaturecat-link": "فهرست عارضه",
    "fcats-link": "فهرست عارضه",
    "parent-link": "والد",
    "related-link": "وابسته",
    "services-link": "سرویس",
    "siblings-link": "Sibling",
    "sources-link": "Source",
    "hassource-link": "Source",
    "source-link": "Source",
    "largerWorkCitation-link": "Larger Work Citation",
    "isTemporalStatOf-link": "Temporal state",
    "stereoMate-link": "Stereo mate",
    "crossReference-link": "Cross Reference",
    "partOfSeamlessDatabase-link": "Part of Seamless Database",
    "isDescriptionOf-link": "شرح",
    "inclusive": "Inclusive",
    "exclusive": "Exclusive"
}